entest/__init__.py
entest/cli.py
entest/const.py
entest/dependency_decorator.py
entest/graph.py
entest/py.typed
entest/runner.py
entest/snoop.py
entest/status_report.py
entest-0.1.16.dist-info/METADATA
entest-0.1.16.dist-info/WHEEL
entest-0.1.16.dist-info/entry_points.txt
entest-0.1.16.dist-info/RECORD
