Metadata-Version: 2.1
Name: entest
Version: 0.1.16
Summary: Write dependent integration tests. See my pycon talk.
Home-page: https://github.com/peteris-zealid/entest
Keywords: test,integration-test
Author: Peteris Ratnieks
Author-email: peteris.ratnieks@zealid.com
Requires-Python: >=3.8,<4.0
Classifier: Programming Language :: Python :: 3
Classifier: Programming Language :: Python :: 3.8
Classifier: Programming Language :: Python :: 3.9
Classifier: Programming Language :: Python :: 3.10
Classifier: Programming Language :: Python :: 3.11
Classifier: Topic :: Software Development :: Testing
Classifier: Typing :: Typed
Provides-Extra: all
Provides-Extra: pysnooper
Provides-Extra: rich
Provides-Extra: stackprinter
Project-URL: Repository, https://github.com/peteris-zealid/entest
